[{"Key":{"CompilationParameters":{"BasePageType":null,"IsDocumentModel":true,"CacheCode":2066397536},"CompilerCacheKey":{"LayoutLocation":null,"ViewStartLocation":null,"ContentCacheCode":0,"CacheCode":685193},"CacheCode":-365478528},"Value":"razor/ljiczzrg.vch.dll"},{"Key":{"CompilationParameters":{"BasePageType":null,"IsDocumentModel":true,"CacheCode":2066397536},"CompilerCacheKey":{"LayoutLocation":null,"ViewStartLocation":null,"ContentCacheCode":-1073550431,"CacheCode":-1072865238},"CacheCode":-1439028959},"Value":"razor/vhfltgta.pu2.dll"},{"Key":{"CompilationParameters":{"BasePageType":null,"IsDocumentModel":true,"CacheCode":2066397536},"CompilerCacheKey":{"LayoutLocation":"_layout-simple","ViewStartLocation":"\u0000D:/git/github/jcoleson.github.io/colesonstatiq/input/index.cshtml\u0000","ContentCacheCode":2137308650,"CacheCode":1867380025},"CacheCode":1501216304},"Value":"razor/nk3egbvl.bjm.dll"},{"Key":{"CompilationParameters":{"BasePageType":null,"IsDocumentModel":true,"CacheCode":2066397536},"CompilerCacheKey":{"LayoutLocation":null,"ViewStartLocation":null,"ContentCacheCode":-555159147,"CacheCode":-554473954},"CacheCode":-920637675},"Value":"razor/zqqhkuhe.xa2.dll"},{"Key":{"CompilationParameters":{"BasePageType":null,"IsDocumentModel":true,"CacheCode":2066397536},"CompilerCacheKey":{"LayoutLocation":"_layout-simple","ViewStartLocation":"\u0000D:/git/github/jcoleson.github.io/colesonstatiq/input/test.cshtml\u0000","ContentCacheCode":-826807512,"CacheCode":-101302798},"CacheCode":-467466519},"Value":"razor/qj2i0bj0.5fj.dll"},{"Key":{"CompilationParameters":{"BasePageType":null,"IsDocumentModel":false,"CacheCode":0},"CompilerCacheKey":{"LayoutLocation":null,"ViewStartLocation":null,"ContentCacheCode":1165403577,"CacheCode":1166088770},"CacheCode":1166110873},"Value":"razor/lp2xsfh3.xtc.dll"},{"Key":{"CompilationParameters":{"BasePageType":null,"IsDocumentModel":false,"CacheCode":0},"CompilerCacheKey":{"LayoutLocation":null,"ViewStartLocation":null,"ContentCacheCode":-397862831,"CacheCode":-397177638},"CacheCode":-397155535},"Value":"razor/amnkedsh.mwa.dll"},{"Key":{"CompilationParameters":{"BasePageType":null,"IsDocumentModel":false,"CacheCode":0},"CompilerCacheKey":{"LayoutLocation":null,"ViewStartLocation":null,"ContentCacheCode":649773530,"CacheCode":650458723},"CacheCode":650480826},"Value":"razor/kbf0bw3v.jrm.dll"},{"Key":{"CompilationParameters":{"BasePageType":null,"IsDocumentModel":false,"CacheCode":0},"CompilerCacheKey":{"LayoutLocation":null,"ViewStartLocation":null,"ContentCacheCode":911738040,"CacheCode":912423233},"CacheCode":912445336},"Value":"razor/2w0eb0sw.q3b.dll"},{"Key":{"CompilationParameters":{"BasePageType":null,"IsDocumentModel":false,"CacheCode":0},"CompilerCacheKey":{"LayoutLocation":null,"ViewStartLocation":null,"ContentCacheCode":-485493844,"CacheCode":-484808651},"CacheCode":-484786548},"Value":"razor/cjdbvc3l.rrr.dll"},{"Key":{"CompilationParameters":{"BasePageType":null,"IsDocumentModel":false,"CacheCode":0},"CompilerCacheKey":{"LayoutLocation":null,"ViewStartLocation":null,"ContentCacheCode":172078916,"CacheCode":172764109},"CacheCode":172786212},"Value":"razor/kkt1apnn.wqq.dll"},{"Key":{"CompilationParameters":{"BasePageType":null,"IsDocumentModel":false,"CacheCode":0},"CompilerCacheKey":{"LayoutLocation":null,"ViewStartLocation":null,"ContentCacheCode":1310559538,"CacheCode":1311244731},"CacheCode":1311266834},"Value":"razor/zbgbmxrv.3is.dll"}]